letstune/__init__.py
letstune/backend/__init__.py
letstune/backend/facade.py
letstune/backend/repo/__init__.py
letstune/backend/repo/sqlite.py
letstune/backend/runner/__init__.py
letstune/backend/runner/_base.py
letstune/backend/runner/checkpoint.py
letstune/backend/runner/epoch.py
letstune/backend/runner/log.py
letstune/backend/runner/simple.py
letstune/backend/scheduler/__init__.py
letstune/backend/scheduler/epoch.py
letstune/backend/scheduler/simple.py
letstune/params.py
letstune/py.typed
letstune/rand.py
letstune/results/__init__.py
letstune/results/_base.py
letstune/results/epoch.py
letstune/results/simple.py
letstune/trainer.py
letstune-0.3.0.dist-info/LICENSE
letstune-0.3.0.dist-info/METADATA
letstune-0.3.0.dist-info/WHEEL
letstune-0.3.0.dist-info/RECORD
