Metadata-Version: 2.1
Name: letstune
Version: 0.3.0
Summary: Hyper-parameter tuning for the masses!
Home-page: https://www.letstune.org/
License: MIT
Keywords: machine-learning,hyperparameter-tuning,deep-learning
Author: Michał Słapek
Author-email: 28485371+mslapek@users.noreply.github.com
Requires-Python: >=3.10,<3.11
Classifier: License :: OSI Approved :: MIT License
Classifier: Programming Language :: Python :: 3
Classifier: Programming Language :: Python :: 3.10
Requires-Dist: numpy (>=1.22.3,<2.0.0)
Requires-Dist: pandas (>=1.4.2,<2.0.0)
Project-URL: Documentation, https://letstune.readthedocs.io/
Project-URL: Repository, https://github.com/mslapek/letstune
